typst_mcp/__init__.py
typst_mcp/cli.py
typst_mcp/py.typed
typst_mcp/server.py
typst_mcp-0.1.0.dist-info/METADATA
typst_mcp-0.1.0.dist-info/WHEEL
typst_mcp-0.1.0.dist-info/entry_points.txt
typst_mcp-0.1.0.dist-info/RECORD
