Metadata-Version: 2.4
Name: typst-mcp
Version: 0.1.0
Summary: Typst MCP Server
Requires-Python: >=3.12
Requires-Dist: click>=8.2.1
Requires-Dist: mcp[cli]>=1.9.4
Requires-Dist: starlette>=0.47.0
Requires-Dist: uvicorn>=0.34.3
